sgasayhello/__init__.py
sgasayhello-0.1.dist-info/METADATA
sgasayhello-0.1.dist-info/WHEEL
sgasayhello-0.1.dist-info/top_level.txt
sgasayhello-0.1.dist-info/RECORD
