Metadata-Version: 2.1
Name: sgasayhello
Version: 0.1
Summary: Just say Hello
Home-page: UNKNOWN
Author: AbdulkadarBabbar
Author-email: abdulkadar.babbar@sganalytics.com
License: MIT
Platform: UNKNOWN
